[{"line":2,"uri":"file:src/test/resources/features/US1008_SubscribersTablosunaKayitEklemeTesti.feature","id":"us1008-subscribers-tablosuna-kayit-ekleme","keyword":"Feature","name":"US1008 Subscribers tablosuna kayit ekleme","description":"","elements":[{"start_timestamp":"2025-10-19T15:40:38.460Z","line":4,"id":"us1008-subscribers-tablosuna-kayit-ekleme;","type":"scenario","keyword":"Scenario","name":"","description":"","steps":[{"keyword":"Given ","line":6,"match":{"location":"stepdefinitions.LoantechStepdefinitions.kullanici_loantech_database_e_baglanir()"},"name":"kullanici loantech database'e baglanir","result":{"duration":475742000,"status":"passed"}},{"keyword":"When ","line":7,"match":{"location":"stepdefinitions.LoantechStepdefinitions.kullaniciSubscribersTablosundaIdDegeriVeEmailBilgisiOlanBirKayitEkler(java.lang.String,java.lang.String)","arguments":[{"val":"\"29\"","offset":43},{"val":"\"jdbcBitti@jdbc.com\"","offset":65}]},"name":"kullanici subscribers tablosunda id degeri \"29\" ve email bilgisi \"jdbcBitti@jdbc.com\" olan bir kayit ekler","result":{"duration":31758597000,"status":"passed"}},{"keyword":"And ","line":8,"match":{"location":"stepdefinitions.LoantechStepdefinitions.tablosunda_degeri_olan_kaydin_bilgisinin_oldugunu_test_eder(java.lang.String,java.lang.String,java.lang.String,java.lang.String,java.lang.String)","arguments":[{"val":"\"subscribers\"","offset":0},{"val":"\"id\"","offset":25},{"val":"\"29\"","offset":37},{"val":"\"email\"","offset":54},{"val":"\"jdbcBitti@jdbc.com\"","offset":73}]},"name":"\"subscribers\" tablosunda \"id\" degeri \"29\" olan kaydin \"email\" bilgisinin \"jdbcBitti@jdbc.com\" oldugunu test eder","result":{"duration":49991000,"status":"passed"}},{"keyword":"And ","line":9,"match":{"location":"stepdefinitions.LoantechStepdefinitions.database_baglantisini_kapatir()"},"name":"database baglantisini kapatir","result":{"duration":2012000,"status":"passed"}}],"tags":[{"name":"@wip"}]}],"tags":[]}]